huaweicloudsdkosm/__init__.py
huaweicloudsdkosm/v2/__init__.py
huaweicloudsdkosm/v2/osm_async_client.py
huaweicloudsdkosm/v2/osm_client.py
huaweicloudsdkosm/v2/model/__init__.py
huaweicloudsdkosm/v2/model/accessory_json_format_req.py
huaweicloudsdkosm/v2/model/accessory_limit_vo.py
huaweicloudsdkosm/v2/model/accessory_url.py
huaweicloudsdkosm/v2/model/agency_v2.py
huaweicloudsdkosm/v2/model/agree_tenant_authorization_v2_req.py
huaweicloudsdkosm/v2/model/agreement_vo.py
huaweicloudsdkosm/v2/model/area_code_simple_info_v2.py
huaweicloudsdkosm/v2/model/case_label_info.py
huaweicloudsdkosm/v2/model/case_query_label.py
huaweicloudsdkosm/v2/model/case_realtion_info.py
huaweicloudsdkosm/v2/model/check_hosts_request.py
huaweicloudsdkosm/v2/model/check_hosts_response.py
huaweicloudsdkosm/v2/model/check_need_verify_request.py
huaweicloudsdkosm/v2/model/check_need_verify_response.py
huaweicloudsdkosm/v2/model/check_verify_codes_request.py
huaweicloudsdkosm/v2/model/check_verify_codes_response.py
huaweicloudsdkosm/v2/model/common_param_v2.py
huaweicloudsdkosm/v2/model/confirm_authorizations_request.py
huaweicloudsdkosm/v2/model/confirm_authorizations_response.py
huaweicloudsdkosm/v2/model/contact_v2.py
huaweicloudsdkosm/v2/model/contact_way_info_v2.py
huaweicloudsdkosm/v2/model/create_and_delete_privilege_req.py
huaweicloudsdkosm/v2/model/create_case_extends_param_request.py
huaweicloudsdkosm/v2/model/create_case_extends_param_response.py
huaweicloudsdkosm/v2/model/create_case_labels_request.py
huaweicloudsdkosm/v2/model/create_case_labels_response.py
huaweicloudsdkosm/v2/model/create_cases_request.py
huaweicloudsdkosm/v2/model/create_cases_response.py
huaweicloudsdkosm/v2/model/create_diagnose_feedback_request.py
huaweicloudsdkosm/v2/model/create_diagnose_feedback_response.py
huaweicloudsdkosm/v2/model/create_diagnose_job_request.py
huaweicloudsdkosm/v2/model/create_diagnose_job_response.py
huaweicloudsdkosm/v2/model/create_feedback_req.py
huaweicloudsdkosm-3.1.184.dist-info/METADATA
huaweicloudsdkosm-3.1.184.dist-info/WHEEL
huaweicloudsdkosm-3.1.184.dist-info/licenses/LICENSE
huaweicloudsdkosm-3.1.184.dist-info/RECORD
